quakesrthorcam/__init__.py
quakesrthorcam/beamfinder.py
quakesrthorcam/thorbridge.py
quakesrthorcam_tspspi-0.0.1a9.dist-info/LICENSE.md
quakesrthorcam_tspspi-0.0.1a9.dist-info/METADATA
quakesrthorcam_tspspi-0.0.1a9.dist-info/WHEEL
quakesrthorcam_tspspi-0.0.1a9.dist-info/entry_points.txt
quakesrthorcam_tspspi-0.0.1a9.dist-info/top_level.txt
quakesrthorcam_tspspi-0.0.1a9.dist-info/RECORD
