Metadata-Version: 2.1
Name: quakesrthorcam-tspspi
Version: 0.0.1a9
Summary: Mini utility that handles pictures taken for QUAK/ESR experiment by ThorCam camera
Home-page: https://github.com/tspspi/quakesrthorcam
Author: Thomas Spielauer
Author-email: pypipackages01@tspi.at
Classifier: Programming Language :: Python :: 3
Classifier: License :: OSI Approved :: BSD License
Classifier: Operating System :: Microsoft :: Windows
Requires-Python: >=3.6
License-File: LICENSE.md
Requires-Dist: paho-mqtt (>=1.6.1)
Requires-Dist: thorcam (>=0.1.6)
Requires-Dist: Pillow (>=9.2.0)
Requires-Dist: paramiko (>=2.11.0)
Requires-Dist: pyopencl (==2021.2.9+cl12)
